bctfcli.py
bctfcli-0.1.4.dist-info/entry_points.txt
bctfcli-0.1.4.dist-info/WHEEL
bctfcli-0.1.4.dist-info/METADATA
bctfcli-0.1.4.dist-info/RECORD
